alternative.py
alternative-0.1.0.dist-info/METADATA
alternative-0.1.0.dist-info/WHEEL
alternative-0.1.0.dist-info/RECORD
