Metadata-Version: 2.4
Name: alternative
Version: 0.1.0
Summary: A library to help with the management of alternative implementations of functions
Author-email: Oliver Bristow <evilumbrella+github@gmail.com>
Requires-Python: >=3.12
Requires-Dist: pytest>=8.3.5
